ProxyMGR/__init__.py
ProxyMGR/manager.py
proxy_mgr-0.1.0.dist-info/METADATA
proxy_mgr-0.1.0.dist-info/WHEEL
proxy_mgr-0.1.0.dist-info/RECORD
